polars_financial/__init__.py
polars_financial/days.py
polars_financial/metrics.py
polars_financial/test/test_metrics.py
polars_financial-0.1.0.dist-info/METADATA
polars_financial-0.1.0.dist-info/WHEEL
polars_financial-0.1.0.dist-info/RECORD
