Metadata-Version: 2.1
Name: polars-financial
Version: 0.1.0
Summary: 
Author: mark.wang
Author-email: wxgter@gmail.com
Requires-Python: >=3.9,<4.0
Classifier: Programming Language :: Python :: 3
Classifier: Programming Language :: Python :: 3.9
Classifier: Programming Language :: Python :: 3.10
Classifier: Programming Language :: Python :: 3.11
Classifier: Programming Language :: Python :: 3.12
Requires-Dist: altair (>=5.4.1,<6.0.0)
Requires-Dist: polars (>=1.6.0,<2.0.0)
